pprint36/__init__.py
pprint36/_pprint.py
pprint36/_pprint.pyi
pprint36/py.typed
pprint36-3.9.16.0.dist-info/LICENSE
pprint36-3.9.16.0.dist-info/METADATA
pprint36-3.9.16.0.dist-info/WHEEL
pprint36-3.9.16.0.dist-info/entry_points.txt
pprint36-3.9.16.0.dist-info/RECORD
