Metadata-Version: 2.1
Name: pprint36
Version: 3.9.16.0
Summary: Backport of pprint from Python 3.9 to Python 3.6-3.8
Author-email: Python Software Foundation <dominic@davis-foster.co.uk>
License: PSFLicense
Keywords: backport,pprint,prettyprint
Home-page: https://github.com/domdfcoding/pprint36
Project-URL: Issue Tracker, https://github.com/domdfcoding/pprint36/issues
Project-URL: Source Code, https://github.com/domdfcoding/pprint36
Platform: Windows
Platform: macOS
Platform: Linux
Classifier: Development Status :: 5 - Production/Stable
Classifier: Intended Audience :: Developers
Classifier: Operating System :: OS Independent
Classifier: Programming Language :: Python
Classifier: Programming Language :: Python :: 3 :: Only
Classifier: Programming Language :: Python :: 3.6
Classifier: Programming Language :: Python :: 3.7
Classifier: Programming Language :: Python :: 3.8
Classifier: Programming Language :: Python :: 3.9
Classifier: Programming Language :: Python :: Implementation :: CPython
Classifier: Topic :: Software Development :: Libraries :: Python Modules
Classifier: Typing :: Typed
Requires-Python: >=3.6
